versalign/aligner.py
versalign/blocking.py
versalign/config.py
versalign/docking.py
versalign/helpers.py
versalign/msa.py
versalign/pairwise.py
versalign/printing.py
versalign/scoring.py
versalign/types.py
versalign/version.py
versalign-2.2.0.dist-info/METADATA
versalign-2.2.0.dist-info/WHEEL
versalign-2.2.0.dist-info/licenses/LICENSE
versalign-2.2.0.dist-info/RECORD
