Metadata-Version: 2.4
Name: versalign
Version: 2.2.0
Summary: Naive alignment for lists of arbitrary objects
Project-URL: Homepage, https://github.com/moltools/versalign
Project-URL: Repository, https://github.com/moltools/versalign
Project-URL: Issues, https://github.com/moltools/versalign/issues
Project-URL: Documentation, https://github.com/moltools/versalign#readme
Author-email: David Meijer <david.meijer@wur.nl>
License-Expression: MIT
License-File: LICENSE
Keywords: alignment,arbitrary-objects,msa,pairwise
Classifier: Development Status :: 5 - Production/Stable
Classifier: Intended Audience :: Science/Research
Classifier: License :: OSI Approved :: MIT License
Classifier: Programming Language :: Python
Classifier: Programming Language :: Python :: 3
Classifier: Programming Language :: Python :: 3.10
Classifier: Programming Language :: Python :: 3.11
Classifier: Programming Language :: Python :: 3.12
Classifier: Topic :: Scientific/Engineering :: Bio-Informatics
Requires-Python: >=3.10
Requires-Dist: biopython
Requires-Dist: numpy
Requires-Dist: pandas
Provides-Extra: dev
Requires-Dist: pytest; extra == 'dev'
Requires-Dist: ruff; extra == 'dev'
